pythonvcs/__init__.py
pythonvcs/gitea.py
pythonvcs-0.0.1.dist-info/LICENSE.md
pythonvcs-0.0.1.dist-info/WHEEL
pythonvcs-0.0.1.dist-info/METADATA
pythonvcs-0.0.1.dist-info/RECORD
