Metadata-Version: 2.1
Name: pythonvcs
Version: 0.0.1
Summary: API wrapper for gitea, pijul nest, etc.
License: Misilelab license v1.6
Author: MisileLaboratory
Requires-Python: >=3.10,<4.0
Classifier: License :: Other/Proprietary License
Classifier: Programming Language :: Python :: 3
Classifier: Programming Language :: Python :: 3.10
Requires-Dist: requests (>=2.27.1,<3.0.0)
